humaware_vad/__init__.py
humaware_vad-0.1.2.dist-info/METADATA
humaware_vad-0.1.2.dist-info/WHEEL
humaware_vad-0.1.2.dist-info/top_level.txt
humaware_vad-0.1.2.dist-info/RECORD
