Metadata-Version: 2.4
Name: humaware-vad
Version: 0.1.2
Summary: HumAwareVAD: A optimized voice activity detection model to better distinguish humming and speech
Home-page: https://github.com/CuriousMonkey7/humaware-vad
Author: Sourabh Saini
Author-email: Sourabh72101@gmail.com
Classifier: Programming Language :: Python :: 3
Classifier: License :: OSI Approved :: MIT License
Classifier: Operating System :: OS Independent
Classifier: Topic :: Scientific/Engineering :: Artificial Intelligence
Classifier: Topic :: Multimedia :: Sound/Audio :: Speech
Requires-Python: >=3.12
Requires-Dist: fastrtc[vad]
Requires-Dist: groq
Requires-Dist: python-dotenv
Requires-Dist: twilio
Requires-Dist: torch
Dynamic: author
Dynamic: author-email
Dynamic: classifier
Dynamic: home-page
Dynamic: requires-dist
Dynamic: requires-python
Dynamic: summary
